ckanext/__init__.py
ckanext/fpx/__init__.py
ckanext/fpx/config.py
ckanext/fpx/helpers.py
ckanext/fpx/interfaces.py
ckanext/fpx/plugin.py
ckanext/fpx/utils.py
ckanext/fpx/views.py
ckanext/fpx/assets/webassets.yml
ckanext/fpx/assets/scripts/fpx-download-starting-toast.js
ckanext/fpx/assets/scripts/fpx-position-tracker-toast.js
ckanext/fpx/assets/scripts/fpx-queue-manager.js
ckanext/fpx/assets/styles/fpx-toast-styles.css
ckanext/fpx/logic/__init__.py
ckanext/fpx/logic/action.py
ckanext/fpx/logic/auth.py
ckanext/fpx/logic/schema.py
ckanext/fpx/logic/validators.py
ckanext/fpx/templates/page.html
ckanext/fpx/templates/fpx/snippets/download_starting_toast.html
ckanext/fpx/templates/fpx/snippets/position_tracker_toast.html
ckanext/fpx/templates/fpx/snippets/static.html
ckanext/fpx/tests/__init__.py
ckanext/fpx/tests/test_helpers.py
ckanext/fpx/tests/test_plugin.py
ckanext/fpx/tests/test_utils.py
ckanext/fpx/tests/logic/__init__.py
ckanext/fpx/tests/logic/test_action.py
ckanext_fpx-0.7.0.dist-info/licenses/LICENSE
ckanext_fpx-0.7.0.dist-info/METADATA
ckanext_fpx-0.7.0.dist-info/WHEEL
ckanext_fpx-0.7.0.dist-info/entry_points.txt
ckanext_fpx-0.7.0.dist-info/top_level.txt
ckanext_fpx-0.7.0.dist-info/RECORD
